{
  "insight_id": "INS-039",
  "title": "Sickness-Driven Understaffing Prediction (Hospitality)",
  "vertical": "hospitality",
  "band": "PLAUSIBLE",
  "test_class": "existence",
  "rationale": "1/2 probes returned usable data; remaining probes returned empty or coarser-than-claimed results. | UKHSA dashboard flu headlines API status 404. | UKHSA surveillance landing reachable (status 200).",
  "evidence": [
    {
      "source": "ukhsa.dashboard",
      "url": "https://ukhsa-dashboard.data.gov.uk/api/topics/Influenza/headlines",
      "accessed_at": "2026-05-03T20:57:08.005460+00:00",
      "http_status": 404,
      "response_sha256": "673d821d9f221701ba4c037fb385b4bfae62d827bb2805f642a42ca38e2597d6",
      "query_params": {},
      "summary": "Flu headlines"
    },
    {
      "source": "ukhsa.gov_uk",
      "url": "https://www.gov.uk/government/statistics/national-flu-and-covid-19-surveillance-reports-2024-to-2025-season",
      "accessed_at": "2026-05-03T20:57:08.704560+00:00",
      "http_status": 200,
      "response_sha256": "e8c19c95686c6d2190e95c673a530a50ef79ee38b683603e29e32bef10625621",
      "query_params": {},
      "summary": "Surveillance landing"
    }
  ],
  "metrics": {
    "probes_total": 2,
    "probes_passed": 1
  },
  "run_at": "2026-05-03T20:57:08.706144+00:00",
  "code_sha": "e495cee",
  "agent": "Devon-4234",
  "notes": ""
}
